riskit/__init__.py
riskit/annotations.py
riskit/factory.py
riskit/sampler.py
riskit/type.py
riskit/compute/__init__.py
riskit/compute/infer.py
riskit/compute/backend/__init__.py
riskit/compute/backend/accelerated.py
riskit/compute/backend/basic.py
riskit/compute/backend/factory.py
riskit/compute/distribution/__init__.py
riskit/compute/distribution/accelerated.py
riskit/compute/distribution/basic.py
riskit/compute/distribution/factory.py
riskit/convergence/__init__.py
riskit/convergence/analyze.py
riskit/convergence/collect.py
riskit/convergence/common.py
riskit/convergence/fit.py
riskit/convergence/summary.py
riskit/convergence/visualize.py
riskit/monitor/__init__.py
riskit/monitor/monitor.py
riskit/monitor/visualize.py
riskit/risk/__init__.py
riskit/risk/common.py
riskit/risk/cvar.py
riskit/risk/entropic.py
riskit/risk/expected.py
riskit/risk/var.py
riskit/risk/variance.py
riskit-0.3.0.dist-info/METADATA
riskit-0.3.0.dist-info/WHEEL
riskit-0.3.0.dist-info/licenses/LICENSE
riskit-0.3.0.dist-info/RECORD
