Metadata-Version: 2.4
Name: riskit
Version: 0.3.0
Summary: A library providing implementations of various risk metrics for risk-aware trajectory planning.
Author-email: Zurab Mujirishvili <zurab.mujirishvili@fau.de>
License-File: LICENSE
Keywords: autonomous systems,risk metrics,robotics,safety,trajectory planning,uncertainty quantification
Classifier: Development Status :: 1 - Planning
Classifier: Intended Audience :: Science/Research
Classifier: License :: OSI Approved :: MIT License
Classifier: Programming Language :: Python :: 3
Classifier: Programming Language :: Python :: 3.13
Classifier: Topic :: Scientific/Engineering :: Artificial Intelligence
Classifier: Typing :: Typed
Requires-Python: >=3.13
Requires-Dist: jax>=0.9.0
Requires-Dist: jaxtyping>=0.3.6
Requires-Dist: numtypes>=0.5.1
Provides-Extra: type-checking
Requires-Dist: beartype>=0.22.9; extra == 'type-checking'
Provides-Extra: visualization
Requires-Dist: anyio>=4.12.1; extra == 'visualization'
Requires-Dist: kaleido>=1.2.0; extra == 'visualization'
Requires-Dist: plotly>=6.5.2; extra == 'visualization'
Requires-Dist: rich>=14.3.1; extra == 'visualization'
Requires-Dist: scipy>=1.17.0; extra == 'visualization'
